<?xml version="1.0" encoding="utf-8"?>
<openerp>
    <data noupdate='1'>
<!-- Nhat Ky Tai San -->
        
        <record id="seq_nhat_ky_tai_san_item" model="ir.sequence">
            <field name="name">Nhật ký tài sản</field>
            <field name="date_get">1</field>
            <field name="rollback_rule">Monthly</field>
            <field name="active">1</field>
            <field name="prefix">TSCĐ-%(year)s%(month)s</field>
            <field name="padding">4</field>
            <field name="number_next_actual">1</field>
            <field name="number_increment">1</field>
            <field name="implementation">no_gap</field>
        </record>

        
              
	</data>
</openerp>